MANIFEST.in
requirements.txt
setup.cfg
setup.py
Harambe.egg-info/PKG-INFO
Harambe.egg-info/SOURCES.txt
Harambe.egg-info/dependency_links.txt
Harambe.egg-info/entry_points.txt
Harambe.egg-info/not-zip-safe
Harambe.egg-info/requires.txt
Harambe.egg-info/top_level.txt
harambe/.DS_Store
harambe/__about__.py
harambe/__about__.pyc
harambe/__init__.py
harambe/__init__.pyc
harambe/cli.py
harambe/cli.pyc
harambe/core.py
harambe/core.pyc
harambe/decorators.py
harambe/decorators.pyc
harambe/exceptions.py
harambe/exceptions.pyc
harambe/ext.py
harambe/ext.pyc
harambe/utils.py
harambe/utils.pyc
harambe/__pycache__/__about__.cpython-35.pyc
harambe/__pycache__/__about__.cpython-36.pyc
harambe/__pycache__/__init__.cpython-35.pyc
harambe/__pycache__/__init__.cpython-36.pyc
harambe/__pycache__/cli.cpython-35.pyc
harambe/__pycache__/cli.cpython-36.pyc
harambe/__pycache__/core.cpython-35.pyc
harambe/__pycache__/core.cpython-36.pyc
harambe/__pycache__/decorators.cpython-35.pyc
harambe/__pycache__/decorators.cpython-36.pyc
harambe/__pycache__/exceptions.cpython-35.pyc
harambe/__pycache__/exceptions.cpython-36.pyc
harambe/__pycache__/ext.cpython-35.pyc
harambe/__pycache__/ext.cpython-36.pyc
harambe/__pycache__/utils.cpython-35.pyc
harambe/__pycache__/utils.cpython-36.pyc
harambe/contrib/.DS_Store
harambe/contrib/__init__.py
harambe/contrib/__init__.pyc
harambe/contrib/app_option.py
harambe/contrib/app_option.pyc
harambe/contrib/application_data.py
harambe/contrib/__pycache__/__init__.cpython-35.pyc
harambe/contrib/__pycache__/__init__.cpython-36.pyc
harambe/contrib/auth/__init__.py
harambe/contrib/auth/__init__.pyc
harambe/contrib/auth/decorators.py
harambe/contrib/auth/decorators.pyc
harambe/contrib/auth/exceptions.py
harambe/contrib/auth/exceptions.pyc
harambe/contrib/auth/models.py
harambe/contrib/auth/models.pyc
harambe/contrib/auth/oauth.py
harambe/contrib/auth/oauth.pyc
harambe/contrib/auth/signals.py
harambe/contrib/auth/signals.pyc
harambe/contrib/static/.DS_Store
harambe/contrib/static/assets.yml
harambe/contrib/static/Harambe/jquery-oembed/jquery.oembed.css
harambe/contrib/static/Harambe/jquery-oembed/jquery.oembed.js
harambe/contrib/static/Harambe/lib/css/_mixins.scss
